{
  "name": "password",
  "utterances": {
    "en": [
      "Password",
      "I forgot the password to my university account. How can I change it?",
      "I need a new password",
      "Wrong password",
      "I can't access my university account!",
      "Help resetting password",
      "I can’t seem to sign in, why is it not working and what can I do?",
      "pwd not working",
      "Help me access account",
      "I'm locked out from my account. Please send me a new password.",
      "How do I get a new password?",
      "The authentication doesn't work",
      "I think my account was hacked and I want to fix it.",
      "I have problems signing in. What do I do?",
      "I can't remember my password.",
      "My password was leaked and I need to change it."
    ]
  },
  "slots": [],
  "contexts": [
    "global"
  ]
}